setup.py
spotii/__init__.py
spotii/__main__.py
spotii/channel.py
spotii/config.py
spotii/define.py
spotii/emit.py
spotii/emit_thread.py
spotii/info_test.py
spotii/main.py
spotii/main_paras.py
spotii/multi_inherit.py
spotii/mythread.py
spotii/non_block_queue.py
spotii/version.py
spotii/vkeyboard.py
spotii.egg-info/PKG-INFO
spotii.egg-info/SOURCES.txt
spotii.egg-info/dependency_links.txt
spotii.egg-info/entry_points.txt
spotii.egg-info/requires.txt
spotii.egg-info/top_level.txt
spotii/communication/__init__.py
spotii/communication/change_password.py
spotii/communication/communication.py
spotii/communication/forgot_password.py
spotii/communication/get_report.py
spotii/communication/get_report_email.py
spotii/communication/image_post.py
spotii/communication/ln_web.py
spotii/communication/send_result.py
spotii/communication/sign_in.py
spotii/communication/sign_up.py
spotii/communication/test_report.py
spotii/communication/test_report_email.py
spotii/guifolder/MyStackedWidget.py
spotii/guifolder/MyToolButton.py
spotii/guifolder/__init__.py
spotii/guifolder/back_button.py
spotii/guifolder/gui.py
spotii/guifolder/myStackedWidget.ui
spotii/guifolder/spotii.ui
spotii/guifolder/title_rc.py
spotii/guifolder/wrong_password.py
spotii/guifolder/wrong_password.ui
spotii/guifolder/help_folder/__init__.py
spotii/guifolder/help_folder/help.ui
spotii/guifolder/help_folder/help_wrap.py
spotii/guifolder/help_folder/play.py
spotii/guifolder/help_folder/video.ui
spotii/guifolder/help_folder/whatis.ui
spotii/guifolder/help_folder/whatis_wrap.py
spotii/guifolder/profile_folder/__init__.py
spotii/guifolder/profile_folder/info.py
spotii/guifolder/profile_folder/profile_wrap.py
spotii/guifolder/profile_folder/profile_wrap.ui
spotii/guifolder/profile_folder/profile_detail/__init__.py
spotii/guifolder/profile_folder/profile_detail/_language.py
spotii/guifolder/profile_folder/profile_detail/chg_psw.py
spotii/guifolder/profile_folder/profile_detail/chg_psw.ui
spotii/guifolder/profile_folder/profile_detail/language.py
spotii/guifolder/profile_folder/profile_detail/language.ui
spotii/guifolder/profile_folder/profile_detail/profile_detail.py
