Metadata-Version: 1.0
Name: spotii
Version: 1.0.52
Summary: Look Spot II
Home-page: https://github.com/gxfca/gitTest
Author: Laipac
Author-email: feng.gao@laipac.com
License: UNKNOWN
Platform: UNKNOWN
